{
  "edges": [
    {
      "id": "reactflow__edge-1Output-0x0",
      "source": "1",
      "sourceHandle": "Output",
      "target": "0",
      "targetHandle": "x0",
      "type": "step"
    },
    {
      "id": "reactflow__edge-0Output-2Input",
      "source": "0",
      "sourceHandle": "Output",
      "target": "2",
      "targetHandle": "Input",
      "type": "step"
    },
    {
      "id": "reactflow__edge-1Output-3x0",
      "source": "1",
      "sourceHandle": "Output",
      "target": "3",
      "targetHandle": "x0",
      "type": "step"
    },
    {
      "id": "reactflow__edge-3Output-4Input",
      "source": "3",
      "sourceHandle": "Output",
      "target": "4",
      "targetHandle": "Input",
      "type": "step"
    }
  ],
  "nodes": [
    {
      "data": {
        "accordion": "Communication",
        "display": "bool To String Node",
        "id": "0",
        "inputHandle": [
          {
            "dataType": "bool",
            "name": "x"
          }
        ],
        "label": "bool to string",
        "outputHandle": [
          {
            "dataType": "bool",
            "name": "Output"
          }
        ],
        "parameterValueData": [
          "aaaBBB",
          "ccceee"
        ],
        "primaryType": "LogicalNode",
        "selectedFriendlyNameData": "",
        "selectedServiceData": "",
        "selectedSubServiceData": "",
        "services": [
          {
            "friendlyName": "testFN",
            "nameServices": [
              "testNS1",
              "testNS2"
            ]
          }
        ],
        "stretchable": true,
        "subServices": [],
        "type": "BToSNode",
        "valueData": ""
      },
      "dragging": false,
      "height": 181,
      "id": "0",
      "position": {
        "x": 581.2949199151287,
        "y": 225.2226293208774
      },
      "positionAbsolute": {
        "x": 581.2949199151287,
        "y": 225.2226293208774
      },
      "selected": false,
      "type": "LogicalNode",
      "width": 246
    },
    {
      "data": {
        "accordion": "Input",
        "dataType": "",
        "display": "Digital Input",
        "id": "1",
        "inputHandle": [],
        "label": "Input",
        "outputHandle": [
          {
            "dataType": "bool",
            "name": "Output"
          }
        ],
        "primaryType": "inputNode",
        "selectedFriendlyNameData": "",
        "selectedServiceData": "DI1",
        "selectedSubServiceData": "",
        "services": [
          {
            "friendlyName": "",
            "nameServices": [
              "DI1",
              "DI2",
              "DI3",
              "DI4",
              "DI5",
              "DI6",
              "DI7",
              "DI8"
            ]
          }
        ],
        "stretchable": false,
        "subServices": [],
        "type": "digitalInput",
        "valueData": ""
      },
      "dragging": false,
      "height": 91,
      "id": "1",
      "position": {
        "x": 274.9659483531009,
        "y": 267.0183343548411
      },
      "positionAbsolute": {
        "x": 274.9659483531009,
        "y": 267.0183343548411
      },
      "selected": false,
      "type": "inputNode",
      "width": 221
    },
    {
      "data": {
        "accordion": "Output",
        "dataType": "",
        "display": "Digital output",
        "id": "2",
        "inputHandle": [
          {
            "dataType": "bool",
            "name": "Input"
          }
        ],
        "label": "Output",
        "outputHandle": [],
        "primaryType": "outputNode",
        "selectedFriendlyNameData": "",
        "selectedServiceData": "DO1",
        "selectedSubServiceData": "",
        "services": [
          {
            "friendlyName": "",
            "nameServices": [
              "DO1",
              "DO2",
              "DO3",
              "DO4"
            ]
          }
        ],
        "stretchable": false,
        "subServices": [],
        "type": "digitalOutput",
        "valueData": ""
      },
      "dragging": false,
      "height": 81,
      "id": "2",
      "position": {
        "x": 898.9191283660095,
        "y": 304.05552695802805
      },
      "positionAbsolute": {
        "x": 898.9191283660095,
        "y": 304.05552695802805
      },
      "selected": false,
      "type": "outputNode",
      "width": 221
    },
    {
      "data": {
        "accordion": "Communication",
        "display": "bool To String Node",
        "id": "0",
        "inputHandle": [
          {
            "dataType": "bool",
            "name": "x"
          }
        ],
        "label": "bool to string",
        "outputHandle": [
          {
            "dataType": "bool",
            "name": "Output"
          }
        ],
        "parameterValueData": [
          "fafaf",
          ""
        ],
        "primaryType": "LogicalNode",
        "selectedFriendlyNameData": "",
        "selectedServiceData": "",
        "selectedSubServiceData": "",
        "services": [
          {
            "friendlyName": "testFN",
            "nameServices": [
              "testNS1",
              "testNS2"
            ]
          }
        ],
        "stretchable": true,
        "subServices": [],
        "type": "BToSNode",
        "valueData": ""
      },
      "draggable": true,
      "dragging": false,
      "height": 181,
      "id": "3",
      "position": {
        "x": 582.2949199151287,
        "y": 459.2226293208774
      },
      "positionAbsolute": {
        "x": 582.2949199151287,
        "y": 459.2226293208774
      },
      "selected": false,
      "type": "LogicalNode",
      "width": 246
    },
    {
      "data": {
        "accordion": "Output",
        "dataType": "",
        "display": "Digital output",
        "id": "2",
        "inputHandle": [
          {
            "dataType": "bool",
            "name": "Input"
          }
        ],
        "label": "Output",
        "outputHandle": [],
        "primaryType": "outputNode",
        "selectedFriendlyNameData": "",
        "selectedServiceData": "DO2",
        "selectedSubServiceData": "",
        "services": [
          {
            "friendlyName": "",
            "nameServices": [
              "DO1",
              "DO2",
              "DO3",
              "DO4"
            ]
          }
        ],
        "stretchable": false,
        "subServices": [],
        "type": "digitalOutput",
        "valueData": ""
      },
      "draggable": true,
      "dragging": false,
      "height": 81,
      "id": "4",
      "position": {
        "x": 888.9191283660095,
        "y": 494.05552695802805
      },
      "positionAbsolute": {
        "x": 888.9191283660095,
        "y": 494.05552695802805
      },
      "selected": false,
      "type": "outputNode",
      "width": 221
    }
  ],
  "viewport": {
    "x": -32.919128366009545,
    "y": -47.055526958028054,
    "zoom": 1
  }
}